scalpl/__init__.py
scalpl/scalpl.py
scalpl-0.4.2.dist-info/METADATA
scalpl-0.4.2.dist-info/WHEEL
scalpl-0.4.2.dist-info/top_level.txt
scalpl-0.4.2.dist-info/RECORD
