Metadata-Version: 1.2
Name: scalpl
Version: 0.4.2
Summary: A lightweight wrapper to operate on nested dictionaries seamlessly.
Home-page: https://github.com/ducdetronquito/scalpl
Author: Guillaume Paulet
Author-email: guillaume.paulet@giome.fr
License: Public Domain
Download-URL: https://github.com/ducdetronquito/scalpl/archive/0.4.2.tar.gz
Keywords: dict,nested,proxy,traversable,dictionary,box,addict,munch,scalpl,scalpel,wrapper
Platform: UNKNOWN
Classifier: Intended Audience :: Developers
Classifier: License :: Public Domain
Classifier: Operating System :: OS Independent
Classifier: Natural Language :: English
Classifier: Programming Language :: Python :: 3 :: Only
Classifier: Topic :: Software Development :: Libraries :: Python Modules
Requires-Python: >=3.6
